{
  "authorDailyContributionsMap": {
    "blimyj": [
      {
        "insertions": 7,
        "deletions": 7,
        "date": "2019-10-04",
        "commitResults": [
          {
            "hash": "31d2dbbd4f4205339193f3e73538698a9fe07679",
            "messageTitle": "Edit UG \u0026 DG",
            "messageBody": "",
            "insertions": 7,
            "deletions": 7
          }
        ]
      }
    ],
    "lrchema": [
      {
        "insertions": 21,
        "deletions": 0,
        "date": "2019-10-04",
        "commitResults": [
          {
            "hash": "36aebcbbca36e397bc0bef0874878eeb00ec135a",
            "messageTitle": "Add information on undo command in UG",
            "messageBody": "",
            "insertions": 21,
            "deletions": 0
          }
        ]
      }
    ],
    "mannggoo": [
      {
        "insertions": 4,
        "deletions": 0,
        "date": "2019-09-25",
        "commitResults": [
          {
            "hash": "4a19dccbedfc218160611b23c86c224ed59f34b9",
            "messageTitle": "Walk through tutorial tracing code",
            "messageBody": "",
            "insertions": 4,
            "deletions": 0
          }
        ]
      },
      {
        "insertions": 92,
        "deletions": 99,
        "date": "2019-10-02",
        "commitResults": [
          {
            "hash": "00d734536ba1f1fa9f9176d92c376baa36edf141",
            "messageTitle": "Update AboutUs and ContactUs",
            "messageBody": "",
            "insertions": 25,
            "deletions": 24
          },
          {
            "hash": "f7e3e13f95a07add5b3975a5ee5e2a98e9862b73",
            "messageTitle": "Update User Guide",
            "messageBody": "",
            "insertions": 62,
            "deletions": 73
          },
          {
            "hash": "45e86536db09d45c557d8d819a3af9adeba7eafa",
            "messageTitle": "Update README.adoc",
            "messageBody": "",
            "insertions": 5,
            "deletions": 2
          }
        ]
      }
    ],
    "sianghwee": [
      {
        "insertions": 15,
        "deletions": 18,
        "date": "2019-09-19",
        "commitResults": [
          {
            "hash": "7613e5fd5b346414e818035667a33a42b43258cb",
            "messageTitle": "Update README.adoc",
            "messageBody": "",
            "insertions": 0,
            "deletions": 14
          },
          {
            "hash": "65401dc497821bf801cb59a9e802e6b1aa0a7dc6",
            "messageTitle": "Update README.adoc",
            "messageBody": "",
            "insertions": 14,
            "deletions": 0
          },
          {
            "hash": "c5b9c336eed805ccb987b87ebe134adf93aa85d5",
            "messageTitle": "Update README.adoc",
            "messageBody": "",
            "insertions": 1,
            "deletions": 4
          }
        ]
      },
      {
        "insertions": 94,
        "deletions": 22,
        "date": "2019-10-03",
        "commitResults": [
          {
            "hash": "459a19095838de9c085125601fd92bb0a705d078",
            "messageTitle": "Update DeveloperGuide.adoc",
            "messageBody": "",
            "insertions": 84,
            "deletions": 12
          },
          {
            "hash": "0b0d15eb77d4880ee8caa8aed6eb2d725ab09fcd",
            "messageTitle": "Update DeveloperGuide.adoc",
            "messageBody": "",
            "insertions": 2,
            "deletions": 2
          },
          {
            "hash": "bc9602245a9e9f1cf029feaae16166cee1ff04ba",
            "messageTitle": "Changed header to fit project name",
            "messageBody": "",
            "insertions": 1,
            "deletions": 1
          },
          {
            "hash": "3eb82813cbd469761acaa8dd3d7331acc29d5c3e",
            "messageTitle": "Update user stories",
            "messageBody": "",
            "insertions": 7,
            "deletions": 7
          }
        ]
      },
      {
        "insertions": 1,
        "deletions": 1,
        "date": "2019-10-04",
        "commitResults": [
          {
            "hash": "d5f26ad480147badca5a470773b68c7db32e6d12",
            "messageTitle": "Edit the URL of Travis to point to the right webpage",
            "messageBody": "",
            "insertions": 1,
            "deletions": 1
          }
        ]
      }
    ],
    "Icesiolz": [
      {
        "insertions": 4,
        "deletions": 4,
        "date": "2019-09-19",
        "commitResults": [
          {
            "hash": "bc6e074c9eb9fc8dc29d3b999639f983cbd618aa",
            "messageTitle": "Update UserGuide.adoc",
            "messageBody": "",
            "insertions": 3,
            "deletions": 3
          },
          {
            "hash": "6de457a7039b4457a98189b2be9b614beb604c39",
            "messageTitle": "Update UserGuide.adoc",
            "messageBody": "",
            "insertions": 1,
            "deletions": 1
          }
        ]
      },
      {
        "insertions": 4,
        "deletions": 5,
        "date": "2019-09-20",
        "commitResults": [
          {
            "hash": "bacdef85ed183e927c1ecc5e4bdbe101dad6697d",
            "messageTitle": "Update UserGuide.adoc",
            "messageBody": "",
            "insertions": 4,
            "deletions": 5
          }
        ]
      },
      {
        "insertions": 115,
        "deletions": 311,
        "date": "2019-10-03",
        "commitResults": [
          {
            "hash": "eba31a0236fe26b488e52d58da71dc98fa4d66a8",
            "messageTitle": "Changed MainWindow.fxml to split-screen view.",
            "messageBody": "",
            "insertions": 26,
            "deletions": 262
          },
          {
            "hash": "7f38d161313e0325f8c736657ead2b9fe1649cc4",
            "messageTitle": "MainWindow: Included tabs and removed unnecessary elements like menu.",
            "messageBody": "",
            "insertions": 89,
            "deletions": 49
          }
        ]
      },
      {
        "insertions": 4,
        "deletions": 9,
        "date": "2019-10-04",
        "commitResults": [
          {
            "hash": "05d9f0606c51b6b96aa7daff17ef290c730b68b3",
            "messageTitle": "Debugged to meet checkstyle.",
            "messageBody": "",
            "insertions": 3,
            "deletions": 3
          },
          {
            "hash": "3d1ad278cf2eb9e10ecbfb5fd13047c81ec25580",
            "messageTitle": "Debug checkstyle.",
            "messageBody": "",
            "insertions": 1,
            "deletions": 5
          },
          {
            "hash": "09c238760b5e60325615e09f50804c67c7f7ed99",
            "messageTitle": "Debug checkstyle.",
            "messageBody": "",
            "insertions": 0,
            "deletions": 1
          }
        ]
      }
    ]
  },
  "authorFinalContributionMap": {
    "blimyj": 7,
    "lrchema": 20,
    "mannggoo": 91,
    "sianghwee": 91,
    "Icesiolz": 100
  },
  "authorFileTypeContributionMap": {
    "blimyj": {
      "docs": 7,
      "tests": 0,
      "functional": 0
    },
    "lrchema": {
      "docs": 20,
      "tests": 0,
      "functional": 0
    },
    "mannggoo": {
      "docs": 87,
      "tests": 0,
      "functional": 4
    },
    "sianghwee": {
      "docs": 91,
      "tests": 0,
      "functional": 0
    },
    "Icesiolz": {
      "docs": 8,
      "tests": 1,
      "functional": 91
    }
  },
  "authorContributionVariance": {
    "blimyj": 6.5255647,
    "lrchema": 14.68252,
    "mannggoo": 1213.3033,
    "sianghwee": 474.5779,
    "Icesiolz": 6021.3716
  },
  "authorDisplayNameMap": {
    "blimyj": "CS2103T-T10-3 BRYAN ... N JIE",
    "lrchema": "CS2103T-T10-3 CHAND ...  HEMA",
    "mannggoo": "CS2103T-T10-3 LIM Y ... U HUI",
    "sianghwee": "CS2103T-T10-3 NG SI ...  HWEE",
    "Icesiolz": "CS2103T-T10-3 LOW C ... NG YI"
  }
}
