{
  "authorDailyContributionsMap": {
    "limerencee": [
      {
        "insertions": 0,
        "deletions": 1,
        "date": "2019-09-08",
        "commitResults": [
          {
            "hash": "4d38aa45fb0405e027ac79a5c9379c279b110802",
            "messageTitle": "Remove the codacy badge from README",
            "messageBody": "",
            "insertions": 0,
            "deletions": 1
          }
        ]
      }
    ],
    "krusagiz": [],
    "lightz96": [],
    "lye-jw": [],
    "kensonoenqh": []
  },
  "authorFinalContributionMap": {
    "limerencee": 0,
    "krusagiz": 0,
    "lightz96": 0,
    "lye-jw": 0,
    "kensonoenqh": 0
  },
  "authorFileTypeContributionMap": {
    "limerencee": {
      "java": 0,
      "adoc": 0,
      "fxml": 0,
      "sh": 0,
      "bat": 0,
      "gradle": 0,
      "txt": 0
    },
    "krusagiz": {
      "java": 0,
      "adoc": 0,
      "fxml": 0,
      "sh": 0,
      "bat": 0,
      "gradle": 0,
      "txt": 0
    },
    "lightz96": {
      "java": 0,
      "adoc": 0,
      "fxml": 0,
      "sh": 0,
      "bat": 0,
      "gradle": 0,
      "txt": 0
    },
    "lye-jw": {
      "java": 0,
      "adoc": 0,
      "fxml": 0,
      "sh": 0,
      "bat": 0,
      "gradle": 0,
      "txt": 0
    },
    "kensonoenqh": {
      "java": 0,
      "adoc": 0,
      "fxml": 0,
      "sh": 0,
      "bat": 0,
      "gradle": 0,
      "txt": 0
    }
  },
  "authorContributionVariance": {
    "limerencee": 0.22222221,
    "krusagiz": 0.0,
    "lightz96": 0.0,
    "lye-jw": 0.0,
    "kensonoenqh": 0.0
  },
  "authorDisplayNameMap": {
    "limerencee": "CS2103T-W12-2 POH J ... A HAO",
    "krusagiz": "CS2103T-W12-2 ANG C ... ELVIN",
    "lightz96": "CS2103T-W12-2 LEE B ... QIANG",
    "lye-jw": "CS2103T-W12-2 LYE J ... N WEN",
    "kensonoenqh": "CS2103T-W12-2 OEN Q ... ENSON"
  }
}
